{
  "name": "SKILL UP",
  "symbol": "SU",
  "level_order": [
    "sl0",
    "sl1",
    "sl2",
    "sl3",
    "sl4",
    "sl5",
    "sl6",
    "sl7",
    "sl8",
    "sl9",
    "sl10",
    "sl11",
    "sl12",
    "st0",
    "st1",
    "st2",
    "st3",
    "st4",
    "st5",
    "st6",
    "st7",
    "st8"
  ],
  "folder_order": [
    "LEVELsl0",
    "LEVELsl1",
    "LEVELsl2",
    "LEVELsl3",
    "LEVELsl4",
    "LEVELsl5",
    "LEVELsl6",
    "LEVELsl7",
    "LEVELsl8",
    "LEVELsl9",
    "LEVELsl10",
    "LEVELsl11",
    "LEVELsl12",
    "LEVELst0"
  ],
  "folder_sort_key": "",
  "folder_sort_ascending": true,
  "entry_type": "",
  "data_url": "data.json",
  "compat_prefix": "LEVEL",
  "last_update": "2023\/10\/30",
  "editor_name": "BeMusicSeeker",
  "editor_version": "0.3.5.6",
  "output_date": "2023\/10\/30"
}